{"cameraMode":{"drawMode":0,"name":"Shaded","section":"Shading Mode"},"sceneLighting":false,"audioPlay":false,"sceneViewState":{"m_AlwaysRefresh":false,"showFog":true,"showSkybox":false,"showFlares":true,"showImageEffects":true,"showParticleSystems":true,"showVisualEffectGraphs":true,"m_FxEnabled":true},"in2DMode":false,"pivot":{"x":-18.696786880493165,"y":-11.538459777832032,"z":10.459664344787598},"rotation":{"x":-0.22912219166755677,"y":0.5358299016952515,"z":-0.1538742184638977,"w":-0.7980155944824219},"size":17.914703369140626,"orthographic":false}